cellmaps_coembedding/__init__.py
cellmaps_coembedding/cellmaps_coembeddingcmd.py
cellmaps_coembedding/corum_M.tsv
cellmaps_coembedding/exceptions.py
cellmaps_coembedding/readme_outputs.txt
cellmaps_coembedding/runner.py
cellmaps_coembedding/utils.py
cellmaps_coembedding/muse_sc/__init__.py
cellmaps_coembedding/muse_sc/architecture.py
cellmaps_coembedding/muse_sc/df_utils.py
cellmaps_coembedding/muse_sc/file_utils.py
cellmaps_coembedding/muse_sc/triplet_loss.py
cellmaps_coembedding/protein_gps/__init__.py
cellmaps_coembedding/protein_gps/architecture.py
cellmaps_coembedding/proteinprojector/__init__.py
cellmaps_coembedding/proteinprojector/architecture.py
cellmaps_coembedding-1.5.0.data/scripts/cellmaps_coembeddingcmd.py
cellmaps_coembedding-1.5.0.dist-info/AUTHORS.rst
cellmaps_coembedding-1.5.0.dist-info/LICENSE
cellmaps_coembedding-1.5.0.dist-info/METADATA
cellmaps_coembedding-1.5.0.dist-info/WHEEL
cellmaps_coembedding-1.5.0.dist-info/top_level.txt
cellmaps_coembedding-1.5.0.dist-info/RECORD
