Metadata-Version: 2.1
Name: cellmaps_coembedding
Version: 1.5.0
Summary: A tool to generate coembeddings from IF image embeddings and PPI network embeddings
Home-page: https://github.com/idekerlab/cellmaps_coembedding
Author: Cell Maps team
Author-email: tools@cm4ai.org
License: MIT license
Keywords: cellmaps_coembedding
Classifier: Development Status :: 2 - Pre-Alpha
Classifier: Intended Audience :: Developers
Classifier: License :: OSI Approved :: MIT License
Classifier: Natural Language :: English
Classifier: Programming Language :: Python :: 3.8
Classifier: Programming Language :: Python :: 3.9
Classifier: Programming Language :: Python :: 3.10
Classifier: Programming Language :: Python :: 3.11
License-File: LICENSE
License-File: AUTHORS.rst
Requires-Dist: cellmaps-utils <1.0.0,>=0.4.0
Requires-Dist: phenograph <2.0.0,>=1.5.7
Requires-Dist: numpy <2.0.0,>=1.24.4
Requires-Dist: torch <3.0.0,>=2.0.0
Requires-Dist: pandas <3.0.0,>=2.0.0
Requires-Dist: matplotlib <4.0.0,>=3.7.4
Requires-Dist: dill <0.4.0,>=0.3.8
Requires-Dist: tqdm <5.0.0,>=4.67.1
Requires-Dist: scipy <1.13,>=1.10.1
